mage_ai/__init__.py
mage_ai/ai/__init__.py
mage_ai/ai/constants.py
mage_ai/ai/generator.py
mage_ai/ai/generator_cmds.py
mage_ai/ai/llm_pipeline_wizard.py
mage_ai/api/__init__.py
mage_ai/api/api_context.py
mage_ai/api/constants.py
mage_ai/api/errors.py
mage_ai/api/logging.py
mage_ai/api/middleware.py
mage_ai/api/oauth_scope.py
mage_ai/api/result_set.py
mage_ai/api/utils.py
mage_ai/api/views.py
mage_ai/api/mixins/__init__.py
mage_ai/api/mixins/result_set.py
mage_ai/api/monitors/BaseMonitor.py
mage_ai/api/monitors/__init__.py
mage_ai/api/operations/__init__.py
mage_ai/api/operations/base.py
mage_ai/api/operations/constants.py
mage_ai/api/parsers/BaseParser.py
mage_ai/api/parsers/PipelineScheduleParser.py
mage_ai/api/parsers/RoleParser.py
mage_ai/api/parsers/UserParser.py
mage_ai/api/parsers/__init__.py
mage_ai/api/policies/AutocompleteItemPolicy.py
mage_ai/api/policies/BackfillPolicy.py
mage_ai/api/policies/BasePolicy.py
mage_ai/api/policies/BlockLayoutItemPolicy.py
mage_ai/api/policies/BlockOutputPolicy.py
mage_ai/api/policies/BlockPolicy.py
mage_ai/api/policies/BlockRunPolicy.py
mage_ai/api/policies/BlockTemplatePolicy.py
mage_ai/api/policies/ClientPagePolicy.py
mage_ai/api/policies/ClusterPolicy.py
mage_ai/api/policies/CustomTemplatePolicy.py
mage_ai/api/policies/DataProviderPolicy.py
mage_ai/api/policies/EventRulePolicy.py
mage_ai/api/policies/ExtensionOptionPolicy.py
mage_ai/api/policies/FileContentPolicy.py
mage_ai/api/policies/FilePolicy.py
mage_ai/api/policies/FileVersionPolicy.py
mage_ai/api/policies/FolderPolicy.py
mage_ai/api/policies/GitBranchPolicy.py
mage_ai/api/policies/GitCustomBranchPolicy.py
mage_ai/api/policies/GitFilePolicy.py
mage_ai/api/policies/GlobalDataProductPolicy.py
mage_ai/api/policies/IntegrationDestinationPolicy.py
mage_ai/api/policies/IntegrationSourcePolicy.py
mage_ai/api/policies/IntegrationSourceStreamPolicy.py
mage_ai/api/policies/InteractionPolicy.py
mage_ai/api/policies/KernelPolicy.py
mage_ai/api/policies/LlmPolicy.py
mage_ai-0.9.43.dist-info/LICENSE
mage_ai-0.9.43.dist-info/METADATA
mage_ai-0.9.43.dist-info/WHEEL
mage_ai-0.9.43.dist-info/entry_points.txt
mage_ai-0.9.43.dist-info/top_level.txt
mage_ai-0.9.43.dist-info/RECORD
