Metadata-Version: 2.1
Name: mage-ai
Version: 0.9.43
Summary: Mage is a tool for building and deploying data pipelines.
Home-page: https://github.com/mage-ai/mage-ai
Author: Mage
Author-email: eng@mage.ai
Classifier: Programming Language :: Python :: 3
Classifier: License :: OSI Approved :: Apache Software License
Classifier: Operating System :: OS Independent
Requires-Python: >=3.7
License-File: LICENSE
Requires-Dist: Faker ==4.14.0
Requires-Dist: GitPython ==3.1.34
Requires-Dist: Jinja2 ==3.1.2
Requires-Dist: PyGithub ==1.59.0
Requires-Dist: PyJWT ==2.6.0
Requires-Dist: aiofiles ==22.1.0
Requires-Dist: alembic >=1.7.5
Requires-Dist: bcrypt ==4.0.1
Requires-Dist: croniter ==1.3.7
Requires-Dist: cryptography ==36.0.2
Requires-Dist: dask >=2022.2.0
Requires-Dist: datadog ==0.44.0
Requires-Dist: freezegun ==1.2.2
Requires-Dist: great-expectations ==0.15.50
Requires-Dist: httpx ==0.23.1
Requires-Dist: inflection ==0.5.1
Requires-Dist: ipykernel ==6.15.0
Requires-Dist: ipython ==7.34.0
Requires-Dist: itsdangerous ~=1.1.0
Requires-Dist: joblib >=1.1.0
Requires-Dist: jupyter-server-proxy ==3.2.1
Requires-Dist: jupyter-server ==1.23.5
Requires-Dist: jupyter-client ==7.3.4
Requires-Dist: ldap3 ==2.9.1
Requires-Dist: newrelic ==8.8.0
Requires-Dist: numpy >=1.21.0
Requires-Dist: pandas >=1.3.0
Requires-Dist: polars <=0.19.2
Requires-Dist: protobuf
Requires-Dist: pyarrow ==10.0.1
Requires-Dist: python-dateutil ==2.8.2
Requires-Dist: pytz ==2022.2.1
Requires-Dist: pyyaml ~=6.0
Requires-Dist: redis
Requires-Dist: requests ==2.31.0
Requires-Dist: ruamel.yaml ==0.17.17
Requires-Dist: scikit-learn >=1.0
Requires-Dist: sentry-sdk ==1.19.1
Requires-Dist: simplejson
Requires-Dist: six >=1.15.0
Requires-Dist: sqlalchemy <2.0.0,>=1.4.20
Requires-Dist: terminado ==0.17.1
Requires-Dist: thefuzz[speedup] ==0.19.0
Requires-Dist: tornado ==6.1
Requires-Dist: typer[all] ==0.7.0
Requires-Dist: typing-extensions ==4.5.0
Provides-Extra: ai
Requires-Dist: astor >=0.8.1 ; extra == 'ai'
Requires-Dist: langchain >=0.0.222 ; extra == 'ai'
Requires-Dist: openai <1.0.0,>=0.27.8 ; extra == 'ai'
Provides-Extra: all
Requires-Dist: PyGithub ==1.59.0 ; extra == 'all'
Requires-Dist: astor >=0.8.1 ; extra == 'all'
Requires-Dist: aws-secretsmanager-caching ==1.1.1.5 ; extra == 'all'
Requires-Dist: azure-eventhub ==5.11.2 ; extra == 'all'
Requires-Dist: azure-identity ==1.12.0 ; extra == 'all'
Requires-Dist: azure-keyvault-certificates ==4.6.0 ; extra == 'all'
Requires-Dist: azure-keyvault-secrets ==4.6.0 ; extra == 'all'
Requires-Dist: azure-mgmt-containerinstance ==10.1.0 ; extra == 'all'
Requires-Dist: azure-storage-blob ==12.14.1 ; extra == 'all'
Requires-Dist: boto3 ==1.26.60 ; extra == 'all'
Requires-Dist: botocore ==1.29.60 ; extra == 'all'
Requires-Dist: clickhouse-connect ==0.5.20 ; extra == 'all'
Requires-Dist: confluent-avro ; extra == 'all'
Requires-Dist: db-dtypes ==1.0.5 ; extra == 'all'
Requires-Dist: dbt-bigquery ==1.4.3 ; extra == 'all'
Requires-Dist: dbt-core ==1.4.8 ; extra == 'all'
Requires-Dist: dbt-duckdb ==1.4.2 ; extra == 'all'
Requires-Dist: dbt-postgres ==1.4.8 ; extra == 'all'
Requires-Dist: dbt-redshift ==1.4.0 ; extra == 'all'
Requires-Dist: dbt-snowflake ==1.4.4 ; extra == 'all'
Requires-Dist: dbt-spark ==1.4.3 ; extra == 'all'
Requires-Dist: dbt-sqlserver ==1.4.3 ; extra == 'all'
Requires-Dist: dbt-trino ==1.4.0 ; extra == 'all'
Requires-Dist: dbt-clickhouse ==1.4.0 ; extra == 'all'
Requires-Dist: duckdb ==0.8.1 ; extra == 'all'
Requires-Dist: elasticsearch ==8.9.0 ; extra == 'all'
Requires-Dist: google-api-core ==2.11.0 ; extra == 'all'
Requires-Dist: google-api-python-client ==2.70.0 ; extra == 'all'
Requires-Dist: google-cloud-bigquery ~=3.0 ; extra == 'all'
Requires-Dist: google-cloud-iam ==2.9.0 ; extra == 'all'
Requires-Dist: google-cloud-pubsub ==2.16.0 ; extra == 'all'
Requires-Dist: google-cloud-run ==0.5.0 ; extra == 'all'
Requires-Dist: google-cloud-storage ==2.5.0 ; extra == 'all'
Requires-Dist: great-expectations ==0.15.50 ; extra == 'all'
Requires-Dist: gspread ==5.7.2 ; extra == 'all'
Requires-Dist: influxdb-client ==1.36.1 ; extra == 'all'
Requires-Dist: kafka-python ==2.0.2 ; extra == 'all'
Requires-Dist: kubernetes ==25.3.0 ; extra == 'all'
Requires-Dist: langchain >=0.0.222 ; extra == 'all'
Requires-Dist: ldap3 ==2.9.1 ; extra == 'all'
Requires-Dist: openai <1.0.0,>=0.27.8 ; extra == 'all'
Requires-Dist: opensearch-py ==2.0.0 ; extra == 'all'
Requires-Dist: oracledb ==1.3.1 ; extra == 'all'
Requires-Dist: pika ==1.3.1 ; extra == 'all'
Requires-Dist: pinotdb ==5.1.0 ; extra == 'all'
Requires-Dist: psycopg2-binary ==2.9.3 ; extra == 'all'
Requires-Dist: psycopg2 ==2.9.3 ; extra == 'all'
Requires-Dist: pydruid ==0.6.5 ; extra == 'all'
Requires-Dist: pymongo ==4.3.3 ; extra == 'all'
Requires-Dist: pyodbc ==4.0.35 ; extra == 'all'
Requires-Dist: redshift-connector ==2.0.909 ; extra == 'all'
Requires-Dist: requests-aws4auth ==1.1.2 ; extra == 'all'
Requires-Dist: snowflake-connector-python ==3.2.1 ; extra == 'all'
Requires-Dist: sshtunnel ==0.4.0 ; extra == 'all'
Requires-Dist: thefuzz[speedup] ==0.19.0 ; extra == 'all'
Provides-Extra: azure
Requires-Dist: azure-eventhub ==5.11.2 ; extra == 'azure'
Requires-Dist: azure-identity ==1.12.0 ; extra == 'azure'
Requires-Dist: azure-keyvault-secrets ==4.6.0 ; extra == 'azure'
Requires-Dist: azure-keyvault-certificates ==4.6.0 ; extra == 'azure'
Requires-Dist: azure-mgmt-containerinstance ==10.1.0 ; extra == 'azure'
Requires-Dist: azure-storage-blob ==12.14.1 ; extra == 'azure'
Provides-Extra: bigquery
Requires-Dist: google-cloud-bigquery ~=3.0 ; extra == 'bigquery'
Requires-Dist: db-dtypes ==1.0.5 ; extra == 'bigquery'
Provides-Extra: clickhouse
Requires-Dist: clickhouse-connect ==0.5.20 ; extra == 'clickhouse'
Provides-Extra: dbt
Requires-Dist: dbt-bigquery ==1.4.3 ; extra == 'dbt'
Requires-Dist: dbt-core ==1.4.8 ; extra == 'dbt'
Requires-Dist: dbt-dremio ==1.5.0 ; extra == 'dbt'
Requires-Dist: dbt-duckdb ==1.4.2 ; extra == 'dbt'
Requires-Dist: dbt-postgres ==1.4.8 ; extra == 'dbt'
Requires-Dist: dbt-redshift ==1.4.0 ; extra == 'dbt'
Requires-Dist: dbt-snowflake ==1.4.4 ; extra == 'dbt'
Requires-Dist: dbt-spark ==1.4.3 ; extra == 'dbt'
Requires-Dist: dbt-sqlserver ==1.4.3 ; extra == 'dbt'
Requires-Dist: dbt-trino ==1.4.0 ; extra == 'dbt'
Requires-Dist: dbt-clickhouse ==1.4.0 ; extra == 'dbt'
Provides-Extra: google-cloud-storage
Requires-Dist: google-cloud-storage ==2.5.0 ; extra == 'google-cloud-storage'
Requires-Dist: gspread ==5.7.2 ; extra == 'google-cloud-storage'
Provides-Extra: hdf5
Requires-Dist: tables ==3.7.0 ; extra == 'hdf5'
Provides-Extra: mysql
Requires-Dist: mysql-connector-python ==8.0.31 ; extra == 'mysql'
Provides-Extra: oracle
Requires-Dist: oracledb ==1.3.1 ; extra == 'oracle'
Provides-Extra: postgres
Requires-Dist: psycopg2 ==2.9.3 ; extra == 'postgres'
Requires-Dist: psycopg2-binary ==2.9.3 ; extra == 'postgres'
Requires-Dist: sshtunnel ==0.4.0 ; extra == 'postgres'
Provides-Extra: redshift
Requires-Dist: boto3 ==1.26.60 ; extra == 'redshift'
Requires-Dist: redshift-connector ==2.0.909 ; extra == 'redshift'
Provides-Extra: s3
Requires-Dist: boto3 ==1.26.60 ; extra == 's3'
Requires-Dist: botocore ==1.29.60 ; extra == 's3'
Provides-Extra: snowflake
Requires-Dist: snowflake-connector-python ==3.2.1 ; extra == 'snowflake'
Provides-Extra: spark
Requires-Dist: boto3 ==1.26.60 ; extra == 'spark'
Requires-Dist: botocore ==1.29.60 ; extra == 'spark'
Provides-Extra: streaming
Requires-Dist: confluent-avro ; extra == 'streaming'
Requires-Dist: influxdb-client ==1.36.1 ; extra == 'streaming'
Requires-Dist: kafka-python ==2.0.2 ; extra == 'streaming'
Requires-Dist: opensearch-py ==2.0.0 ; extra == 'streaming'
Requires-Dist: pika ==1.3.1 ; extra == 'streaming'
Requires-Dist: pymongo ==4.3.3 ; extra == 'streaming'
Requires-Dist: requests-aws4auth ==1.1.2 ; extra == 'streaming'
Requires-Dist: elasticsearch ==8.9.0 ; extra == 'streaming'
